pyreclab-0.1.16.data/purelib/pyreclab/__init__.py
pyreclab-0.1.16.data/purelib/pyreclab/libpyreclab.so
pyreclab-0.1.16.dist-info/LICENSE
pyreclab-0.1.16.dist-info/METADATA
pyreclab-0.1.16.dist-info/WHEEL
pyreclab-0.1.16.dist-info/top_level.txt
pyreclab-0.1.16.dist-info/RECORD
