Metadata-Version: 2.1
Name: pyreclab
Version: 0.1.16
Summary: Library for quickly testing and prototyping of traditional recommender system methods
Home-page: https://github.com/gasevi/pyreclab
Author: Gabriel Sepulveda
Author-email: UNKNOWN
License: GPL 3.0
Keywords: recsys recommendation rating ranking
Platform: UNKNOWN
